pyarchernet/__init__.py
pyarchernet/arpc.py
pyarchernet/channel.py
pyarchernet/fair_lock.py
pyarchernet/handlers.py
pyarchernet/http.py
pyarchernet/server_channel.py
pyarchernet/sslcontext.py
pyarchernet/unordered_map.py
pyarchernet/lib/libarchernet.dll
pyarchernet/lib/libarchernet.so
pyarchernet-1.2.8.dist-info/licenses/LICENSE
pyarchernet-1.2.8.dist-info/METADATA
pyarchernet-1.2.8.dist-info/WHEEL
pyarchernet-1.2.8.dist-info/top_level.txt
pyarchernet-1.2.8.dist-info/RECORD
